pyspectral/__init__.py
pyspectral/atm_correction_ir.py
pyspectral/blackbody.py
pyspectral/config.py
pyspectral/near_infrared_reflectance.py
pyspectral/radiance_tb_conversion.py
pyspectral/raw_reader.py
pyspectral/rayleigh.py
pyspectral/rsr_reader.py
pyspectral/solar.py
pyspectral/utils.py
pyspectral/data/MSG_SEVIRI_Spectral_Response_Characterisation.XLS
pyspectral/data/e490_00a.dat
pyspectral/data/modis/EOS-Aqua/01.amb.1pct.det
pyspectral/data/modis/EOS-Aqua/02.amb.1pct.det
pyspectral/data/modis/EOS-Aqua/03.amb.1pct.det
pyspectral/data/modis/EOS-Aqua/04.amb.1pct.det
pyspectral/data/modis/EOS-Aqua/05.tv.1pct.det
pyspectral/data/modis/EOS-Aqua/06.tv.1pct.det
pyspectral/data/modis/EOS-Aqua/07.tv.1pct.det
pyspectral/data/modis/EOS-Aqua/08.amb.1pct.det
pyspectral/data/modis/EOS-Aqua/09.amb.1pct.det
pyspectral/data/modis/EOS-Aqua/10.amb.1pct.det
pyspectral/data/modis/EOS-Aqua/11.amb.1pct.det
pyspectral/data/modis/EOS-Aqua/12.amb.1pct.det
pyspectral/data/modis/EOS-Aqua/13.amb.1pct.det
pyspectral/data/modis/EOS-Aqua/14.amb.1pct.det
pyspectral/data/modis/EOS-Aqua/15.amb.1pct.det
pyspectral/data/modis/EOS-Aqua/16.amb.1pct.det
pyspectral/data/modis/EOS-Aqua/17.amb.1pct.det
pyspectral/data/modis/EOS-Aqua/18.amb.1pct.det
pyspectral/data/modis/EOS-Aqua/19.amb.1pct.det
pyspectral/data/modis/EOS-Aqua/20.tv.1pct.det
pyspectral/data/modis/EOS-Aqua/21.tv.1pct.det
pyspectral/data/modis/EOS-Aqua/22.tv.1pct.det
pyspectral/data/modis/EOS-Aqua/23.tv.1pct.det
pyspectral/data/modis/EOS-Aqua/24.tv.1pct.det
pyspectral/data/modis/EOS-Aqua/25.tv.1pct.det
pyspectral/data/modis/EOS-Aqua/26.tv.1pct.det
pyspectral/data/modis/EOS-Aqua/27.tv.1pct.det
pyspectral/data/modis/EOS-Aqua/28.tv.1pct.det
pyspectral/data/modis/EOS-Aqua/29.tv.1pct.det
pyspectral/data/modis/EOS-Aqua/30.tv.1pct.det
pyspectral/data/modis/EOS-Aqua/31.tv.1pct.det
pyspectral/data/modis/EOS-Aqua/32.tv.1pct.det
pyspectral/data/modis/EOS-Aqua/33.tv.1pct.det
pyspectral/data/modis/EOS-Aqua/34.tv.1pct.det
pyspectral-0.10.2.dist-info/LICENSE.txt
pyspectral-0.10.2.dist-info/METADATA
pyspectral-0.10.2.dist-info/WHEEL
pyspectral-0.10.2.dist-info/top_level.txt
pyspectral-0.10.2.dist-info/RECORD
